colors/__init__.py
colors/colors.py
polidoro_py_colors-1.0.0.dist-info/LICENSE
polidoro_py_colors-1.0.0.dist-info/METADATA
polidoro_py_colors-1.0.0.dist-info/WHEEL
polidoro_py_colors-1.0.0.dist-info/top_level.txt
polidoro_py_colors-1.0.0.dist-info/RECORD
