Metadata-Version: 2.1
Name: polidoro-py-colors
Version: 1.0.0
Summary: Set of constants to simplify print with colors.
Home-page: https://github.com/heitorpolidoro/colors
Author: Heitor Polidoro
License: unlicense
Platform: UNKNOWN
Classifier: Programming Language :: Python :: 3
Classifier: License :: OSI Approved :: MIT License
Classifier: Operating System :: OS Independent
